{
  "appPageId" : "a577f86f-a440-429b-8038-160364b2bca4",
  "componentName" : "siteforce:sldsOneColLayout",
  "dataProviders" : [ ],
  "id" : "9842ddc9-8880-40c6-bfd6-a5d0b4fe29b1",
  "label" : "Messages",
  "regions" : [ {
    "components" : [ {
      "componentAttributes" : { },
      "componentName" : "forceChatter:messages",
      "id" : "b1652b7e-06e8-4d98-a36f-9543b9c177d8",
      "renderPriority" : "NEUTRAL",
      "renditionMap" : { },
      "type" : "component"
    } ],
    "id" : "aba4140a-c074-4795-906f-017446e2241e",
    "regionName" : "content",
    "type" : "region"
  } ],
  "themeLayoutType" : "Inner",
  "type" : "view",
  "viewType" : "messages"
}